LICENSE
MANIFEST.in
README.rst
setup.py
tox.ini
passwheel/__init__.py
passwheel/clipboard.py
passwheel/crypto.py
passwheel/passgen.py
passwheel/util.py
passwheel/wheel.py
passwheel.egg-info/PKG-INFO
passwheel.egg-info/SOURCES.txt
passwheel.egg-info/dependency_links.txt
passwheel.egg-info/entry_points.txt
passwheel.egg-info/requires.txt
passwheel.egg-info/top_level.txt