Metadata-Version: 1.1
Name: passwheel
Version: 0.1.2
Summary: A password and secret personal storage tool.
Home-page: https://bitbucket.org/johannestaas/passwheel
Author: Johan Nestaas
Author-email: johannestaas@gmail.com
License: GPLv3
Keywords: password storage crypto
Platform: UNKNOWN
Classifier: Development Status :: 3 - Alpha
Classifier: Environment :: Console
Classifier: Environment :: X11 Applications :: Qt
Classifier: Environment :: MacOS X
Classifier: Environment :: Win32 (MS Windows)
Classifier: Operating System :: POSIX
Classifier: Operating System :: MacOS :: MacOS X
Classifier: Operating System :: Microsoft :: Windows
Classifier: Programming Language :: Python
